command4bot/__init__.py
command4bot/command.py
command4bot/context.py
command4bot/fallback.py
command4bot/manager.py
command4bot/py.typed
command4bot/typing_ext.py
command4bot-0.4.1.dist-info/WHEEL
command4bot-0.4.1.dist-info/METADATA
command4bot-0.4.1.dist-info/RECORD
