Metadata-Version: 2.1
Name: command4bot
Version: 0.4.1
Summary: A general purpose library for command-based iteraction made for bots
Home-page: https://github.com/AllanChain/command4bot
License: MIT
Keywords: command,bot
Author: Allan Chain
Author-email: allanchain@pku.edu.cn
Requires-Python: >=3.6.1,<4.0.0
Classifier: Development Status :: 3 - Alpha
Classifier: License :: OSI Approved :: MIT License
Classifier: Programming Language :: Python :: 3
Classifier: Programming Language :: Python :: 3.6
Classifier: Programming Language :: Python :: 3.7
Classifier: Programming Language :: Python :: 3.8
Classifier: Programming Language :: Python :: 3.9
Classifier: Topic :: Communications :: Chat
Requires-Dist: typing_extensions (>=3.7.4,<4.0.0); python_version < "3.8"
Project-URL: Documentation, https://command4bot.readthedocs.io/en/latest/
Project-URL: Repository, https://github.com/AllanChain/command4bot
